Metadata-Version: 2.1
Name: bddsync
Version: 1.2.2
Summary: Tools to synchronize BDD files with test management tools like Jira-Xray
Home-page: https://github.com/Manzanero/bddsync
Download-URL: https://github.com/Manzanero/bddsync/archive/refs/tags/v1.2.2.tar.gz
Author: Alejandro Manzanero
Author-email: alejmans@gmail.com
License: MIT
Keywords: bdd,cucumber,behave,jira,xray,testing
Classifier: Development Status :: 4 - Beta
Classifier: Intended Audience :: Developers
Classifier: Topic :: Software Development :: Build Tools
Classifier: License :: OSI Approved :: MIT License
Classifier: Programming Language :: Python :: 3.10
License-File: LICENSE
Requires-Dist: requests
Requires-Dist: PyYAML
